quantumwerewolf/backend.py
quantumwerewolf/cli.py
quantumwerewolf-3.6.1.dist-info/LICENSE
quantumwerewolf-3.6.1.dist-info/METADATA
quantumwerewolf-3.6.1.dist-info/WHEEL
quantumwerewolf-3.6.1.dist-info/entry_points.txt
quantumwerewolf-3.6.1.dist-info/top_level.txt
quantumwerewolf-3.6.1.dist-info/RECORD
