Metadata-Version: 2.2
Name: quantumwerewolf
Version: 3.6.1
Summary: Quantum version of the werewolves party game.
License: MIT License
Project-URL: Homepage, https://github.com/ProodjePindakaas/Quantum-Werewolf
Project-URL: Bug Tracker, https://github.com/ProodjePindakaas/Quantum-Werewolf/issues
Keywords: quantum,werewolf,werewolves,game
Classifier: Programming Language :: Python :: 3
Classifier: License :: OSI Approved :: MIT License
Classifier: Operating System :: OS Independent
Requires-Python: >=3.8
License-File: LICENSE
